Metadata-Version: 2.1
Name: tap-pipedrive
Version: 1.3.1
Summary: Singer.io tap for extracting data from the Pipedrive API
Home-page: http://singer.io
Author: Stitch
Author-email: dev@stitchdata.com
Classifier: Programming Language :: Python :: 3 :: Only
License-File: LICENSE
Requires-Dist: pendulum==3.1.0
Requires-Dist: requests==2.32.4
Requires-Dist: singer-python==6.1.1
